pubkeeper/communication/websocket/__init__.py
pubkeeper/communication/websocket/client.py
pubkeeper/communication/websocket/server.py
pubkeeper.communication.websocket-0.2.5.dist-info/DESCRIPTION.rst
pubkeeper.communication.websocket-0.2.5.dist-info/METADATA
pubkeeper.communication.websocket-0.2.5.dist-info/RECORD
pubkeeper.communication.websocket-0.2.5.dist-info/WHEEL
pubkeeper.communication.websocket-0.2.5.dist-info/metadata.json
pubkeeper.communication.websocket-0.2.5.dist-info/top_level.txt
