Metadata-Version: 2.0
Name: pubkeeper.communication.websocket
Version: 0.2.5
Summary: Brew, Fill, Consume
Home-page: http://github.com/pubkeeper/python-communication-websocket
Author: n.io
Author-email: info@n.io
License: UNKNOWN
Keywords: pubkeeper,communication-websocket
Platform: UNKNOWN
Classifier: License :: Other/Proprietary License
Classifier: Programming Language :: Python :: 3
Classifier: Programming Language :: Python :: 3.5
Requires-Dist: pubkeeper.communication (>=0.2.0)
Requires-Dist: tornado
